openhdemg/__init__.py
openhdemg/compatibility/__init__.py
openhdemg/compatibility/conversions.py
openhdemg/gui/__init__.py
openhdemg/gui/__main__.py
openhdemg/gui/backup_settings.py
openhdemg/gui/openhdemg_gui.py
openhdemg/gui/settings.py
openhdemg/gui/gui_files/Cite.png
openhdemg/gui/gui_files/Contact.png
openhdemg/gui/gui_files/Error.png
openhdemg/gui/gui_files/Gear.png
openhdemg/gui/gui_files/Icon_transp.ico
openhdemg/gui/gui_files/Info.png
openhdemg/gui/gui_files/Logo_high_res.png
openhdemg/gui/gui_files/Matrix.png
openhdemg/gui/gui_files/Online.png
openhdemg/gui/gui_files/Redirect.png
openhdemg/gui/gui_files/gui_color_theme.json
openhdemg/gui/gui_modules/__init__.py
openhdemg/gui/gui_modules/advanced_analyses.py
openhdemg/gui/gui_modules/analyse_force.py
openhdemg/gui/gui_modules/edit_mus.py
openhdemg/gui/gui_modules/edit_sig.py
openhdemg/gui/gui_modules/error_handler.py
openhdemg/gui/gui_modules/gui_helpers.py
openhdemg/gui/gui_modules/gui_plotting.py
openhdemg/gui/gui_modules/mu_properties.py
openhdemg/library/__init__.py
openhdemg/library/analysis.py
openhdemg/library/electrodes.py
openhdemg/library/info.py
openhdemg/library/mathtools.py
openhdemg/library/muap.py
openhdemg/library/openfiles.py
openhdemg/library/pic.py
openhdemg/library/plotemg.py
openhdemg/library/tools.py
openhdemg/library/decomposed_test_files/otb_testfile.mat
openhdemg/tests/fixtures/__init__.py
openhdemg/tests/integration/__init__.py
openhdemg/tests/unit/__init__.py
openhdemg/tests/unit/functions_for_unit_test.py
openhdemg/tests/unit/test_anlysis.py
openhdemg/tests/unit/test_electrodes.py
openhdemg/tests/unit/test_info.py
openhdemg/tests/unit/test_mathtools.py
openhdemg/tests/unit/test_muap.py
openhdemg/tests/unit/test_openfiles.py
openhdemg/tests/unit/test_pic.py
openhdemg/tests/unit/test_plotemg.py
openhdemg/tests/unit/test_tools.py
openhdemg-0.1.2.dist-info/LICENSE
openhdemg-0.1.2.dist-info/METADATA
openhdemg-0.1.2.dist-info/WHEEL
openhdemg-0.1.2.dist-info/top_level.txt
openhdemg-0.1.2.dist-info/RECORD
