Metadata-Version: 2.2
Name: openhdemg
Version: 0.1.2
Summary: Open-source analysis of High-Density EMG data
Maintainer: Giacomo Valli
Maintainer-email: giacomo.valli@unibs.it
License: GPL-3.0
Project-URL: Documentation, https://giacomovalli.com/openhdemg
Project-URL: Release Notes, https://giacomovalli.com/openhdemg/what%27s-new
Project-URL: Source Code, https://github.com/GiacomoValliPhD/openhdemg
Project-URL: Bug Tracker, https://github.com/GiacomoValliPhD/openhdemg/issues
Classifier: Intended Audience :: Science/Research
Classifier: Programming Language :: Python :: 3.10
Classifier: Programming Language :: Python :: 3.11
Classifier: Programming Language :: Python :: 3.12
Classifier: Programming Language :: Python :: 3.13
Classifier: Topic :: Scientific/Engineering
Classifier: Topic :: Scientific/Engineering :: Human Machine Interfaces
Classifier: Topic :: Scientific/Engineering :: Medical Science Apps.
Classifier: Operating System :: POSIX
Classifier: Operating System :: Unix
Classifier: Operating System :: MacOS
License-File: LICENSE
Requires-Dist: customtkinter==5.2.2
Requires-Dist: CTkMessagebox==2.7
Requires-Dist: matplotlib==3.9.3
Requires-Dist: numpy<=2.2.0
Requires-Dist: openpyxl==3.1.5
Requires-Dist: pandas==2.2.3
Requires-Dist: pandastable==0.13.1
Requires-Dist: scipy<=1.14.1
Requires-Dist: seaborn==0.13.2
Requires-Dist: scikit-learn==1.5.2
Dynamic: classifier
Dynamic: description
Dynamic: description-content-type
Dynamic: license
Dynamic: maintainer
Dynamic: maintainer-email
Dynamic: project-url
Dynamic: requires-dist
Dynamic: summary
